extract_office_content/__init__.py
extract_office_content/extract_excel.py
extract_office_content/extract_ppt.py
extract_office_content/extract_word.py
extract_office_content/main.py
extract_office_content/utils.py
extract_office_content-0.0.7.dist-info/METADATA
extract_office_content-0.0.7.dist-info/WHEEL
extract_office_content-0.0.7.dist-info/entry_points.txt
extract_office_content-0.0.7.dist-info/top_level.txt
extract_office_content-0.0.7.dist-info/RECORD
