Metadata-Version: 2.1
Name: extract-office-content
Version: 0.0.7
Summary: Tool for extracting content from office files.
Home-page: https://github.com/SWHL/ExtractOfficeText.git
Author: SWHL
Author-email: liekkaskono@163.com
License: Apache-2.0
Keywords: extract,office,text,content
Platform: Any
Classifier: Programming Language :: Python :: 3.6
Classifier: Programming Language :: Python :: 3.7
Classifier: Programming Language :: Python :: 3.8
Classifier: Programming Language :: Python :: 3.9
Classifier: Programming Language :: Python :: 3.10
Classifier: Programming Language :: Python :: 3.11
Requires-Python: >=3.6,<3.12
Requires-Dist: lxml (>=4.9.1)
Requires-Dist: openpyxl (>=3.1.2)
Requires-Dist: pandas (>=1.3.5)
Requires-Dist: pytest (>=7.1.2)
Requires-Dist: python-docx (>=0.8.11)
Requires-Dist: python-pptx (>=0.6.21)
Requires-Dist: tabulate
Requires-Dist: filetype
